gap_mapper/__init__.py
gap_mapper/core.py
gap_mapper-0.2.0.dist-info/licenses/LICENCE
gap_mapper-0.2.0.dist-info/METADATA
gap_mapper-0.2.0.dist-info/WHEEL
gap_mapper-0.2.0.dist-info/top_level.txt
gap_mapper-0.2.0.dist-info/RECORD
