Metadata-Version: 2.4
Name: gap-mapper
Version: 0.2.0
Summary: Add your description here
Project-URL: Homepage, https://github.com/Soct/gap-mapper
Project-URL: Repository, https://github.com/Soct/gap-mapper
Project-URL: Bug Tracker, https://github.com/Soct/gap-mapper/issues
Requires-Python: >=3.12
License-File: LICENCE
Dynamic: license-file
